liiatools/__init__.py
liiatools/__main__.py
liiatools/datasets/__init__.py
liiatools/datasets/annex_a/README.md
liiatools/datasets/annex_a/__init__.py
liiatools/datasets/annex_a/annex_a_cli.py
liiatools/datasets/annex_a/lds_annexa_clean/__init__.py
liiatools/datasets/annex_a/lds_annexa_clean/cleaner.py
liiatools/datasets/annex_a/lds_annexa_clean/configuration.py
liiatools/datasets/annex_a/lds_annexa_clean/converters.py
liiatools/datasets/annex_a/lds_annexa_clean/degrade.py
liiatools/datasets/annex_a/lds_annexa_clean/file_creator.py
liiatools/datasets/annex_a/lds_annexa_clean/logger.py
liiatools/datasets/annex_a/lds_annexa_clean/populate.py
liiatools/datasets/annex_a/lds_annexa_clean/regex.py
liiatools/datasets/annex_a/lds_annexa_la_agg/__init__.py
liiatools/datasets/annex_a/lds_annexa_la_agg/configuration.py
liiatools/datasets/annex_a/lds_annexa_la_agg/process.py
liiatools/datasets/annex_a/lds_annexa_pan_agg/__init__.py
liiatools/datasets/annex_a/lds_annexa_pan_agg/configuration.py
liiatools/datasets/annex_a/lds_annexa_pan_agg/process.py
liiatools/datasets/cin_census/__init__.py
liiatools/datasets/cin_census/cin_cli.py
liiatools/datasets/cin_census/lds_cin_clean/__init__.py
liiatools/datasets/cin_census/lds_cin_clean/cin_record.py
liiatools/datasets/cin_census/lds_cin_clean/configuration.py
liiatools/datasets/cin_census/lds_cin_clean/converter.py
liiatools/datasets/cin_census/lds_cin_clean/file_creator.py
liiatools/datasets/cin_census/lds_cin_clean/filters.py
liiatools/datasets/cin_census/lds_cin_clean/logger.py
liiatools/datasets/cin_census/lds_cin_clean/parse.py
liiatools/datasets/cin_census/lds_cin_clean/schema.py
liiatools/datasets/cin_census/lds_cin_clean/validator.py
liiatools/datasets/cin_census/lds_cin_la_agg/__init__.py
liiatools/datasets/cin_census/lds_cin_la_agg/configuration.py
liiatools/datasets/cin_census/lds_cin_la_agg/process.py
liiatools/datasets/cin_census/lds_cin_pan_agg/__init__.py
liiatools/datasets/cin_census/lds_cin_pan_agg/configuration.py
liiatools-0.2.0.dist-info/LICENSE
liiatools-0.2.0.dist-info/METADATA
liiatools-0.2.0.dist-info/WHEEL
liiatools-0.2.0.dist-info/RECORD
